{"252": {"files": ["/blog/wp-content/uploads/2016/07/Selecci\u00f3n_055.png", "/blog/wp-content/uploads/2016/07/Selecci\u00f3n_055-150x150.png", "/blog/wp-content/uploads/2016/07/Selecci\u00f3n_055-300x176.png", "/blog/wp-content/uploads/2016/07/Selecci\u00f3n_055-768x451.png", "/blog/wp-content/uploads/2016/07/Selecci\u00f3n_055-320x188.png"], "files_meta": [{"width": 816, "height": 479}, {"size": "thumbnail", "width": 150, "height": 150}, {"size": "medium", "width": 300, "height": 176}, {"size": "medium_large", "width": 768, "height": 451}, {"size": "teaser", "width": 320, "height": 188}], "title": "Selecci\u00f3n_055", "date_utc": "2016-07-05 01:45:48", "wordpress_user_name": "andres"}, "253": {"files": ["/blog/wp-content/uploads/2016/07/Selecci\u00f3n_057.png", "/blog/wp-content/uploads/2016/07/Selecci\u00f3n_057-150x150.png", "/blog/wp-content/uploads/2016/07/Selecci\u00f3n_057-300x204.png", "/blog/wp-content/uploads/2016/07/Selecci\u00f3n_057-768x522.png", "/blog/wp-content/uploads/2016/07/Selecci\u00f3n_057-320x217.png"], "files_meta": [{"width": 876, "height": 595}, {"size": "thumbnail", "width": 150, "height": 150}, {"size": "medium", "width": 300, "height": 204}, {"size": "medium_large", "width": 768, "height": 522}, {"size": "teaser", "width": 320, "height": 217}], "title": "Selecci\u00f3n_057", "date_utc": "2016-07-05 02:03:35", "wordpress_user_name": "andres"}, "254": {"files": ["/blog/wp-content/uploads/2016/07/Selecci\u00f3n_058.png", "/blog/wp-content/uploads/2016/07/Selecci\u00f3n_058-150x150.png", "/blog/wp-content/uploads/2016/07/Selecci\u00f3n_058-300x238.png", "/blog/wp-content/uploads/2016/07/Selecci\u00f3n_058-320x254.png"], "files_meta": [{"width": 702, "height": 558}, {"size": "thumbnail", "width": 150, "height": 150}, {"size": "medium", "width": 300, "height": 238}, {"size": "teaser", "width": 320, "height": 254}], "title": "Selecci\u00f3n_058", "date_utc": "2016-07-05 02:29:56", "wordpress_user_name": "andres"}}